{"1_faqs.md":"c4865f3e","1_main-concepts.md":"ad309206","2_browserrouter.md":"f90e83e4","2_hashrouter.md":"1f79f107","2_historyrouter.md":"6511b571","2_memoryrouter.md":"feecb979","2_nativerouter.md":"ebd4c5b5","2_router.md":"ce2da81b","2_staticrouter.md":"91f2b668","3_link-react-native.md":"452f8ae5","3_link.md":"69529a0e","3_navlink.md":"c7bcaef8","3_navigate.md":"e6355126","3_outlet.md":"1a0be89c","3_route-and-routes.md":"f05e2079","4_usehref.md":"6949f561","4_useinroutercontext.md":"f169f9dc","4_uselinkclickhandler.md":"a347988b","4_uselinkpresshandler.md":"87749595","4_uselocation.md":"770482bf","4_usematch.md":"57e9bcab","4_usenavigate.md":"8ecb2bf8","4_usenavigationtype.md":"0075f285","4_useoutlet.md":"7d78dee3","4_useoutletcontext.md":"cacead5c","4_useparams.md":"a10a2987","4_useresolvedpath.md":"0b75b21b","4_useroutes.md":"5ffe992c","4_usesearchparams-react-native.md":"ecfbc727","4_usesearchparams.md":"8a61d560","5_location.md":"432e4407","5_createroutesfromchildren.md":"d5aebc9d","5_createsearchparams.md":"b7bbd7d5","5_generatepath.md":"42650338","5_matchpath.md":"c6c8ecdc","5_matchroutes.md":"9f740347","5_rendermatches.md":"889914f3","5_resolvepath.md":"77440d56"}
